{
"type": "FeatureCollection",
"name": "fire station",
"crs": { "type": "name", "properties": { "name": "urn:ogc:def:crs:OGC:1.3:CRS84" } },
"features": [
{ "type": "Feature", "properties": { "full_id": "w372206664", "osm_id": "372206664", "amenity": "fire_station", "name": "Пожарная часть № 106", "building:levels": "1", "building": "yes", "alt_name": "Пожарная часть № 106 Гатчинского района", "addr:street": "Белогорское шоссе", "addr:housenumber": "14", "addr:city": "Сиверский", "type": "fire_station" }, "geometry": { "type": "Point", "coordinates": [ 30.084385389920548, 59.352717362469427 ] } }
]
}
