{
"type": "FeatureCollection",
"name": "florist",
"crs": { "type": "name", "properties": { "name": "urn:ogc:def:crs:OGC:1.3:CRS84" } },
"features": [
{ "type": "Feature", "properties": { "fid": 1, "name": "Цветы Людмила", "address": "просп. Героев, 2А ", "addr:subdistrict": "городской поселок Сиверский" }, "geometry": { "type": "Point", "coordinates": [ 30.037883798150531, 59.345216337159719 ] } },
{ "type": "Feature", "properties": { "fid": 2, "name": "Магазин цветов", "address": "ул. Вокзальная, 3", "addr:subdistrict": "городской поселок Сиверский" }, "geometry": { "type": "Point", "coordinates": [ 30.066001198662917, 59.355350317016324 ] } },
{ "type": "Feature", "properties": { "fid": 3, "name": "Агромагазин Росток", "address": "ул. Строителей, 1 ", "addr:subdistrict": "городской поселок Сиверский" }, "geometry": { "type": "Point", "coordinates": [ 30.066093653977763, 59.354403126189233 ] } },
{ "type": "Feature", "properties": { "fid": 4, "name": "Питомник растений Greengost", "address": "просп. Вырицкий, 114", "addr:subdistrict": "деревня Куровицы" }, "geometry": { "type": "Point", "coordinates": [ 30.141859182570599, 59.394029564351158 ] } }
]
}
