{
"type": "FeatureCollection",
"name": "mfz",
"crs": { "type": "name", "properties": { "name": "urn:ogc:def:crs:OGC:1.3:CRS84" } },
"features": [
{ "type": "Feature", "properties": { "full_id": null, "osm_id": null, "amenity": "mfz", "name": "Социальный фонд России", "type": null }, "geometry": { "type": "Point", "coordinates": [ 30.070907610361978, 59.355679223448952 ] } }
]
}
