{
"type": "FeatureCollection",
"name": "museum",
"crs": { "type": "name", "properties": { "name": "urn:ogc:def:crs:OGC:1.3:CRS84" } },
"features": [
{ "type": "Feature", "properties": { "element_type": "node", "osmid": 5659183323, "name": "Дом-музей Исаака Шварца", "website": "https://museum-schvarz.ru/" }, "geometry": { "type": "Point", "coordinates": [ 30.12521, 59.3574934 ] } },
{ "type": "Feature", "properties": { "element_type": null, "osmid": null, "name": "Дачная столица", "website": "http://www.gatchina.biz/dachnaya" }, "geometry": { "type": "Point", "coordinates": [ 30.093668829469838, 59.365597555124872 ] } }
]
}
