{
"type": "FeatureCollection",
"name": "police",
"crs": { "type": "name", "properties": { "name": "urn:ogc:def:crs:OGC:1.3:CRS84" } },
"features": [
{ "type": "Feature", "properties": { "full_id": "n5181609743", "osm_id": "5181609743", "osm_type": "node", "amenity": "police", "type": "police", "name": "106 отдел полиции Гатчинского района Ленинградской области" }, "geometry": { "type": "Point", "coordinates": [ 30.061925, 59.344597 ] } }
]
}
