{
"type": "FeatureCollection",
"name": "social_facility",
"crs": { "type": "name", "properties": { "name": "urn:ogc:def:crs:OGC:1.3:CRS84" } },
"features": [
{ "type": "Feature", "properties": { "full_id": null, "osm_id": null, "amenity": "social_facility", "name": "Медико-социальный центр Родительский дом", "type": "social_facility" }, "geometry": { "type": "Point", "coordinates": [ 30.090296921387111, 59.356862120392741 ] } },
{ "type": "Feature", "properties": { "full_id": null, "osm_id": null, "amenity": "social_facility", "name": "Сиверский ресурсный центр", "type": "social_facility" }, "geometry": { "type": "Point", "coordinates": [ 30.081014038871583, 59.362421896247554 ] } }
]
}
