{
"type": "FeatureCollection",
"name": "bank",
"crs": { "type": "name", "properties": { "name": "urn:ogc:def:crs:OGC:1.3:CRS84" } },
"features": [
{ "type": "Feature", "properties": { "element_type": "node", "osmid": 3715247875, "amenity": "bank", "atm": "yes", "brand": "Сбербанк", "brand:en": "Sberbank", "brand:ru": "Сбербанк", "brand:wikidata": "Q205012", "brand:wikipedia": "en:Sberbank of Russia", "name": "Сбербанк", "name:en": "Sberbank", "name:ru": "Сбербанк", "operator": "Сбербанк России", "branch": null, "contact:facebook": null, "contact:instagram": null, "contact:ok": null, "contact:phone": null, "contact:twitter": null, "contact:vk": null, "contact:website": null, "contact:youtube": null, "opening_hours": null, "operator:wikidata": null, "operator:wikipedia": null, "ref": null, "source": null, "wheelchair": null }, "geometry": { "type": "Point", "coordinates": [ 30.0657232, 59.353894305113812 ] } },
{ "type": "Feature", "properties": { "element_type": "node", "osmid": 6425852098, "amenity": "bank", "atm": null, "brand": "Сбербанк", "brand:en": "Sberbank", "brand:ru": "Сбербанк", "brand:wikidata": "Q205012", "brand:wikipedia": "en:Sberbank of Russia", "name": "Сбербанк", "name:en": "Sberbank", "name:ru": "Сбербанк", "operator": "ПАО Сбербанк", "branch": "Северо-Западный банк", "contact:facebook": "https://www.facebook.com/sberbank", "contact:instagram": "https://instagram.com/sberbank", "contact:ok": "https://ok.ru/sberbank", "contact:phone": "+7 800 5555550", "contact:twitter": "https://twitter.com/sberbank/", "contact:vk": "https://vk.com/sberbank", "contact:website": "https://www.sberbank.ru/", "contact:youtube": "https://www.youtube.com/sberbank", "opening_hours": "We,Fr 09:00-13:00,14:00-16:30", "operator:wikidata": "Q205012", "operator:wikipedia": "ru:Сбербанк России", "ref": "9055/0908", "source": "https://www.sberbank.ru/", "wheelchair": "no" }, "geometry": { "type": "Point", "coordinates": [ 30.1308695, 59.3490246 ] } },
{ "type": "Feature", "properties": { "element_type": null, "osmid": null, "amenity": null, "atm": null, "brand": null, "brand:en": null, "brand:ru": null, "brand:wikidata": null, "brand:wikipedia": null, "name": "Почта Банк", "name:en": null, "name:ru": null, "operator": null, "branch": null, "contact:facebook": null, "contact:instagram": null, "contact:ok": null, "contact:phone": null, "contact:twitter": null, "contact:vk": null, "contact:website": null, "contact:youtube": null, "opening_hours": null, "operator:wikidata": null, "operator:wikipedia": null, "ref": null, "source": null, "wheelchair": null }, "geometry": { "type": "Point", "coordinates": [ 30.064697518750044, 59.356494033204264 ] } },
{ "type": "Feature", "properties": { "element_type": null, "osmid": null, "amenity": null, "atm": null, "brand": null, "brand:en": null, "brand:ru": null, "brand:wikidata": null, "brand:wikipedia": null, "name": null, "name:en": null, "name:ru": null, "operator": null, "branch": null, "contact:facebook": null, "contact:instagram": null, "contact:ok": null, "contact:phone": null, "contact:twitter": null, "contact:vk": null, "contact:website": null, "contact:youtube": null, "opening_hours": null, "operator:wikidata": null, "operator:wikipedia": null, "ref": null, "source": null, "wheelchair": null }, "geometry": { "type": "Point", "coordinates": [ 30.04975845473734, 59.351811181304178 ] } }
]
}
