{
"type": "FeatureCollection",
"name": "books",
"crs": { "type": "name", "properties": { "name": "urn:ogc:def:crs:OGC:1.3:CRS84" } },
"features": [
{ "type": "Feature", "properties": { "name": "Книги" }, "geometry": { "type": "Point", "coordinates": [ 30.066540967522897, 59.354451168141217 ] } },
{ "type": "Feature", "properties": { "name": null }, "geometry": { "type": "Point", "coordinates": [ 30.04169102018108, 59.354531628159755 ] } }
]
}
