{
"type": "FeatureCollection",
"name": "notary",
"crs": { "type": "name", "properties": { "name": "urn:ogc:def:crs:OGC:1.3:CRS84" } },
"features": [
{ "type": "Feature", "properties": { "name": "Нотариусы" }, "geometry": { "type": "Point", "coordinates": [ 30.067133774097336, 59.35711655603918 ] } },
{ "type": "Feature", "properties": { "name": null }, "geometry": { "type": "Point", "coordinates": [ 30.048723387662172, 59.355101598828348 ] } }
]
}
